pyTooling/GenericPath/URL.py
pyTooling/GenericPath/__init__.py
pyTooling.GenericPath-0.2.5.dist-info/LICENSE.md
pyTooling.GenericPath-0.2.5.dist-info/METADATA
pyTooling.GenericPath-0.2.5.dist-info/WHEEL
pyTooling.GenericPath-0.2.5.dist-info/top_level.txt
pyTooling.GenericPath-0.2.5.dist-info/RECORD
