Metadata-Version: 2.1
Name: pyTooling.GenericPath
Version: 0.2.5
Summary: A generic path implementation to derive domain specific path libraries.
Home-page: https://GitHub.com/pyTooling/pyTooling.GenericPath
Author: Patrick Lehmann
Author-email: Paebbels@gmail.com
License: Apache-2.0
Project-URL: Documentation, https://pyTooling.GitHub.io/pyTooling.GenericPath
Project-URL: Source Code, https://GitHub.com/pyTooling/pyTooling.GenericPath
Project-URL: Issue Tracker, https://GitHub.com/pyTooling/pyTooling.GenericPath/issues
Keywords: path,generic path,generic library,url
Platform: UNKNOWN
Classifier: Operating System :: OS Independent
Classifier: Intended Audience :: Developers
Classifier: Topic :: Utilities
Classifier: License :: OSI Approved :: Apache Software License
Classifier: Programming Language :: Python :: 3 :: Only
Classifier: Programming Language :: Python :: 3.7
Classifier: Programming Language :: Python :: 3.8
Classifier: Programming Language :: Python :: 3.9
Classifier: Programming Language :: Python :: 3.10
Classifier: Development Status :: 4 - Beta
Requires-Python: >=3.7
License-File: LICENSE.md
Requires-Dist: pyTooling (>=1.9.5)
Requires-Dist: py-flags (>=1.1.4)
Provides-Extra: all
Requires-Dist: pyTooling (>=1.9.5) ; extra == 'all'
Requires-Dist: sphinx-rtd-theme (>=0.5.2) ; extra == 'all'
Requires-Dist: sphinx (>=4.4.0) ; extra == 'all'
Requires-Dist: sphinx-autodoc-typehints (>=1.17.0) ; extra == 'all'
Requires-Dist: py-flags (>=1.1.4) ; extra == 'all'
Requires-Dist: sphinx-fontawesome (>=0.0.6) ; extra == 'all'
Provides-Extra: doc
Requires-Dist: pyTooling (>=1.9.5) ; extra == 'doc'
Requires-Dist: sphinx-rtd-theme (>=0.5.2) ; extra == 'doc'
Requires-Dist: sphinx (>=4.4.0) ; extra == 'doc'
Requires-Dist: sphinx-autodoc-typehints (>=1.17.0) ; extra == 'doc'
Requires-Dist: py-flags (>=1.1.4) ; extra == 'doc'
Requires-Dist: sphinx-fontawesome (>=0.0.6) ; extra == 'doc'
